CategorizerAI-0.4.3.data/scripts/CategorizerAI
categorizerai/CategorizerService.py
categorizerai/__init__.py
categorizerai/ai/AccuracyCheckService.py
categorizerai/ai/NeuralNetBuilderService.py
categorizerai/ai/NeuralNetTrainerService.py
categorizerai/ai/__init__.py
categorizerai/data/NumericConverterService.py
categorizerai/data/PrepareDataService.py
categorizerai/data/__init__.py
categorizerai/db/CategoryService.py
categorizerai/db/ConnectionService.py
categorizerai/db/RowProviderService.py
categorizerai/db/UpdateDBService.py
categorizerai/db/__init__.py
categorizerai/ui/AccuracyErrorDisplayService.py
categorizerai/ui/ChoiceAskService.py
categorizerai/ui/DisplayAccuracyService.py
categorizerai/ui/OptionDisplayService.py
categorizerai/ui/TransactionDisplayService.py
categorizerai/ui/__init__.py
categorizerai/update/ChoiceObtainerService.py
categorizerai/update/OptionPreparatorService.py
categorizerai/update/RowUpdateService.py
categorizerai/update/UpdateService.py
categorizerai/update/__init__.py
CategorizerAI-0.4.3.dist-info/METADATA
CategorizerAI-0.4.3.dist-info/WHEEL
CategorizerAI-0.4.3.dist-info/top_level.txt
CategorizerAI-0.4.3.dist-info/RECORD
