Metadata-Version: 2.1
Name: CategorizerAI
Version: 0.4.3
Summary: An AI to categorize finantial transactions
Home-page: https://github.com/kode-konveyor/categorizerai
Author: Arpad Magosanyi
Author-email: mag@kodekonveyor.com
License: UNKNOWN
Platform: UNKNOWN
Classifier: Programming Language :: Python :: 3
Classifier: License :: OSI Approved :: GNU General Public License v3 or later (GPLv3+)
Classifier: Operating System :: OS Independent
Requires-Dist: tensorflow
Requires-Dist: keras
Requires-Dist: pandas
Requires-Dist: psycopg2-binary
Requires-Dist: winterboot (>=0.3)
